latch_sdk_gql/__init__.py
latch_sdk_gql/execute.py
latch_sdk_gql/utils.py
latch_sdk_gql-0.0.7.dist-info/LICENSE
latch_sdk_gql-0.0.7.dist-info/METADATA
latch_sdk_gql-0.0.7.dist-info/WHEEL
latch_sdk_gql-0.0.7.dist-info/top_level.txt
latch_sdk_gql-0.0.7.dist-info/RECORD
